dbinterface/__init__.py
dbinterface/database_client.py
dbinterface/database_interface.py
dbinterface/db2_client.py
dbinterface/mixins.py
dbinterface/mysql_client.py
dbinterface/postgres_client.py
dbinterface/utils.py
somenzz/__init__.py
somenzz/db/__init__.py
somenzz/db/database_client.py
somenzz/db/database_interface.py
somenzz/db/db2_client.py
somenzz/db/mysql_client.py
somenzz/db/postgres_client.py
somenzz/db/utils.py
dbinterface-0.6.dist-info/LICENSE
dbinterface-0.6.dist-info/METADATA
dbinterface-0.6.dist-info/WHEEL
dbinterface-0.6.dist-info/top_level.txt
dbinterface-0.6.dist-info/RECORD
