Metadata-Version: 2.1
Name: dbinterface
Version: 0.6
Summary: UNKNOWN
Home-page: https://github.com/somenzz/dbinterface
Author: somenzz
Author-email: somenzz@163.com
License: MIT
Keywords: python database client interface
Platform: UNKNOWN
Classifier: Development Status :: 3 - Alpha
Classifier: Intended Audience :: Developers
Classifier: License :: OSI Approved :: MIT License
Classifier: Operating System :: OS Independent
Classifier: Programming Language :: Python
Classifier: Programming Language :: Python :: 3
Classifier: Topic :: Software Development
Classifier: Topic :: Software Development :: Libraries :: Python Modules
Classifier: Topic :: Utilities
License-File: LICENSE
